Workbook
Name AGREGADOSECOMPONENTES1COLABORADOR: [1]GERAL!$G$22
Name CANAL1COLABORADOR: [1]GERAL!$G$14
Name CANAL2COLABORADORES: [1]GERAL!$G$15
Name COLADEIRA1COLABORADOR: [1]GERAL!$G$9
Name COLADEIRA2COLABORADORES: [1]GERAL!$G$10
Name COLAGEMMANUAL1COLABORADOR: [1]GERAL!$G$11
Name EMBALAGEM1COLOBORADOR: [1]GERAL!$G$31
Name EMBALAGEM2COLABORADORES: [1]GERAL!$G$30
Name F2001COLABORADOR: [1]GERAL!$G$18
Name F2002COLABORADORES: [1]GERAL!$G$19
Name HETTICH1COLABORADOR: [1]GERAL!$G$20
Name HETTICH2COLABORADORES: [1]GERAL!$G$21
Name LIMPEZAESEPARACAO1COLABORADOR: [1]GERAL!$G$13
Name LIMPEZAESEPARACAO2COLABORADORES: [1]GERAL!$G$12
Name MONTAGEMDUPLAMEIOPROFISSIONALAJUDANTE: [1]GERAL!$G$26
Name MONTAGEMDUPLAPROFISSIONALAJUDANTE: [1]GERAL!$G$25
Name MONTAGEMEASSISTENCIAPROFISSIONAL: [1]GERAL!$G$35
Name MONTAGEMEASSISTENCIAPROFISSIONALMEIOOFICIAL: [1]GERAL!$G$33
Name MONTAGEMEASSISTENCIAPROFISSIONALPROFISSIONAL: [1]GERAL!$G$32
Name MONTAGEMEASSSISTENCIAPROFISSIONALAJUDANTE: [1]GERAL!$G$34
Name MONTAGEMEQUIPE3COLABORES: [1]GERAL!$G$23
Name MONTAGEMINDIVIDUALMEIOOFICIAL: [1]GERAL!$G$28
Name SECCIONADORA1COLABORADOR: [1]GERAL!$G$4
Name SECCIONADORA2COLABORADORES: [1]GERAL!$G$3
Name SEPARACAOECONFERENCIA1COLABORADOR: [1]GERAL!$G$6
Name SEPARACAOECONFERENCIA2COLABORADORES: [1]GERAL!$G$5
Name UNIAOEENGROSSO1COLABORADOR: [1]GERAL!$G$8
Name UNIAOEENGROSSO2COLABORADORES: [1]GERAL!$G$7
Name USINAGEM1COLABORADOR: [1]GERAL!$G$17
Name USINAGEM2COLABORADORES: [1]GERAL!$G$16

Sheet CADASTRO CLIENTE
C2: CADASTRO DO CLIENTE
D3: ATUALIZAÇÃO DA PLANILHA: | E3: 10.01.20
D4: VERSÃO: | E4: V1
A5: DATA: | C5: 10.01.20
A6: CLIENTE:
A7: EMPREENDIMENTO:
A8: AMBIENTE:
A9: PRODUTO:

Sheet MATERIAIS
F1: DATA: | G1: 45613
B2: LEVANTAMENTO DE MATERIAIS | F2: CLIENTE: | G2: ='CADASTRO CLIENTE'!C6 -> 0
F3: EMPREENDIMENTO: | G3: ='CADASTRO CLIENTE'!C7 -> 0
B4: ATUALIZAÇÃO DA PLANILHA: | C4: ='CADASTRO CLIENTE'!E3 -> 10.01.20 | F4: AMBIENTE: | G4: ='CADASTRO CLIENTE'!C8 -> 0
F5: PRODUTO: | G5: ='CADASTRO CLIENTE'!C9 -> 0
B6: PRODUTO / MATERIAL | C6: UNIDADE | D6: CUSTO FINAL DOS MATERIAIS | E6: QUANTIDADE | F6: CUSTO X QUANTIDADE | G6: % POR CATEGORIA | H6: % GLOBAL
A7: TOTAL | F7: =F8+F25+F42+F91+F109+F167+F171+F177+F194+F205 -> 0 | H7: 1
A8: CHAPAS DE MDF | F8: =F9+F15 -> 0 | G8: 1 | H8: =F8*$H$7/$F$7 -> #DIV/0!
B9: BRANCO - MDF | F9: =SUM(F10:F14) -> 0 | G9: =F9*$G$8/$F$8 -> #DIV/0! | H9: =F9*$H$7/$F$7 -> #DIV/0!
B10: MDF Branco Tx 06mm | C10: CHAPA | D10: 164 | F10: =D10*E10 -> 0 | G10: =F10*$G$8/$F$8 -> #DIV/0! | H10: =F10*$H$7/$F$7 -> #DIV/0! | XDI10: =SUM(E10:XDH10) -> #DIV/0!
B11: MDF Branco TX 15mm | C11: CHAPA | D11: 220 | F11: =D11*E11 -> 0 | G11: =F11*$G$8/$F$8 -> #DIV/0! | H11: =F11*$H$7/$F$7 -> #DIV/0! | XDI11: =SUM(E11:XDH11) -> #DIV/0!
B12: MDF Branco Tx 18mm | C12: CHAPA | D12: 0 | E12: 0 | F12: =D12*E12 -> 0 | G12: =F12*$G$8/$F$8 -> #DIV/0! | H12: =F12*$H$7/$F$7 -> #DIV/0! | XDI12: =SUM(E12:XDH12) -> #DIV/0!
B13: MDF Branco 15 mm NAVAL | C13: CHAPA | D13: 320 | F13: =D13*E13 -> 0 | G13: =F13*$G$8/$F$8 -> #DIV/0! | H13: =F13*$H$7/$F$7 -> #DIV/0! | XDI13: =SUM(E13:XDH13) -> #DIV/0!
B15: UNICOLORES e AMADEIRADO - MDF | F15: =SUM(F16:F23) -> 0 | G15: =F15*$G$8/$F$8 -> #DIV/0! | H15: =F15*$H$7/$F$7 -> #DIV/0!
B16: MDF Unicolor TX 06mm | C16: CHAPA | D16: 250 | E16: 0 | F16: =D16*E16 -> 0 | G16: =F16*$G$8/$F$8 -> #DIV/0! | H16: =F16*$H$7/$F$7 -> #DIV/0!
B17: MDF Unicolor TX 15mm | C17: CHAPA | D17: 400 | F17: =D17*E17 -> 0 | G17: =F17*$G$8/$F$8 -> #DIV/0! | H17: =F17*$H$7/$F$7 -> #DIV/0!
B18: MDF Unicolor Tx 18mm | C18: CHAPA | D18: 0 | F18: =D18*E18 -> 0 | G18: =F18*$G$8/$F$8 -> #DIV/0! | H18: =F18*$H$7/$F$7 -> #DIV/0!
B19: MDF Amadeirado 06mm | C19: CHAPA | D19: 250 | F19: =D19*E19 -> 0 | G19: =F19*$G$8/$F$8 -> #DIV/0! | H19: =F19*$H$7/$F$7 -> #DIV/0!
B20: MDF Amadeirado 15mm | C20: CHAPA | D20: 400 | F20: =D20*E20 -> 0 | G20: =F20*$G$8/$F$8 -> #DIV/0! | H20: =F20*$H$7/$F$7 -> #DIV/0!
B21: MDF Amadeirado 18mm | C21: CHAPA | D21: 0 | E21: 0 | F21: =D21*E21 -> 0 | G21: =F21*$G$8/$F$8 -> #DIV/0! | H21: =F21*$H$7/$F$7 -> #DIV/0!
B22: MDF Amadeirado 25mm | C22: CHAPA | D22: 0 | E22: 0 | F22: =D22*E22 -> 0 | G22: =F22*$G$8/$F$8 -> #DIV/0! | H22: =F22*$H$7/$F$7 -> #DIV/0!
A25: FITA DE BORDA | F25: =F26+F34 -> 0 | G25: 1 | H25: =F25*$H$7/$F$7 -> #DIV/0!
B26: BRANCA - FITA DE BORDA 0,45mm | F26: =SUM(F27:F33) -> 0 | G26: =F26*$G$25/$F$25 -> #DIV/0! | H26: =F26*$H$7/$F$7 -> #DIV/0!
B27: Fita de Borda Branco Tx 22mm(Metros) - 0,45mm | C27: METRO | D27: 30 | E27: 0 | F27: =D27*E27 -> 0 | G27: =F27*$G$25/$F$25 -> #DIV/0! | H27: =F27*$H$7/$F$7 -> #DIV/0!
B28: Fita de Borda Branco Tx 29mm (Metros) - 0,45mm | C28: METRO | D28: 0 | E28: 0 | F28: =D28*E28 -> 0 | G28: =F28*$G$25/$F$25 -> #DIV/0! | H28: =F28*$H$7/$F$7 -> #DIV/0!
B29: Fita de Borda Branco Tx 35mm (Metros) - 0,45mm | C29: METRO | D29: 0 | E29: 0 | F29: =D29*E29 -> 0 | G29: =F29*$G$25/$F$25 -> #DIV/0! | H29: =F29*$H$7/$F$7 -> #DIV/0!
B31: Fita de Borda Branco Tx 22 (Metros) - 1,00mm | C31: METRO | D31: 0 | E31: 0 | F31: =D31*E31 -> 0 | G31: =F31*$G$25/$F$25 -> #DIV/0! | H31: =F31*$H$7/$F$7 -> #DIV/0!
B32: Fita de Borda Branco Tx 35 (Metros) - 1,00mm | C32: METRO | D32: 0 | E32: 0 | F32: =D32*E32 -> 0 | G32: =F32*$G$25/$F$25 -> #DIV/0! | H32: =F32*$H$7/$F$7 -> #DIV/0!
B34: AMADEIRADO - FITA DE BORDA 1,00mm | F34: =SUM(F35:F41) -> 0 | G34: =F34*$G$25/$F$25 -> #DIV/0! | H34: =F34*$H$7/$F$7 -> #DIV/0!
B35: Fita de Borda Amadeirado 22mm (Rolo) - 0,45mm | C35: ROLO 50M | D35: 80 | F35: =D35*E35 -> 0 | G35: =F35*$G$25/$F$25 -> #DIV/0! | H35: =F35*$H$7/$F$7 -> #DIV/0!
B36: Fita de Borda Amadeirado 40mm (Rolo) - 0,45mm | C36: ROLO 20M | D36: 54 | F36: =D36*E36 -> 0 | G36: =F36*$G$25/$F$25 -> #DIV/0! | H36: =F36*$H$7/$F$7 -> #DIV/0!
B37: Fita de Borda Amadeirado 64mm (Rolo) - 0,45mm | C37: ROLO 25M | D37: 94 | E37: 0 | F37: =D37*E37 -> 0 | G37: =F37*$G$25/$F$25 -> #DIV/0! | H37: =F37*$H$7/$F$7 -> #DIV/0!
B39: Fita de Borda Amadeirado Tx 22 (ROLO - 25 METROS) - 1,00 mm | C39: ROLO 25M | D39: 0 | E39: 0 | F39: =D39*E39 -> 0 | G39: =F39*$G$25/$F$25 -> #DIV/0! | H39: =F39*$H$7/$F$7 -> #DIV/0!
B40: Fita de Borda Amadeirado Tx 35 (ROLO - 25 METROS) - 1,00 mm | C40: ROLO 25M | D40: 0 | E40: 0 | F40: =D40*E40 -> 0 | G40: =F40*$G$25/$F$25 -> #DIV/0! | H40: =F40*$H$7/$F$7 -> #DIV/0!
A42: ACESSÓRIOS | F42: =F43+F52+F60+F68+F78 -> 0 | G42: 1 | H42: =F42*$H$7/$F$7 -> #DIV/0!
B43: Suportes | F43: =SUM(F44:F51) -> 0 | G43: =F43*$G$42/$F$42 -> #DIV/0! | H43: =F43*$H$7/$F$7 -> #DIV/0!
B44: VB (Pino + VB 19mm BRANCO/ PRETO) - DUPLO | C44: UNIDADE | D44: 0 | E44: 0 | F44: =D44*E44 -> 0 | G44: =F44*$G$42/$F$42 -> #DIV/0! | H44: =F44*$H$7/$F$7 -> #DIV/0!
B45: Pino Cromado | C45: UNIDADE | D45: 0 | E45: 0 | F45: =D45*E45 -> 0 | G45: =F45*$G$42/$F$42 -> #DIV/0! | H45: =F45*$H$7/$F$7 -> #DIV/0!
B46: Pino de Plástico | C46: UNIDADE | D46: 0 | E46: 0 | F46: =D46*E46 -> 0 | G46: =F46*$G$42/$F$42 -> #DIV/0! | H46: =F46*$H$7/$F$7 -> #DIV/0!
B47: Cantoneira Cromada 2 Furos | C47: UNIDADE | D47: 0.25 | E47: 0 | F47: =D47*E47 -> 0 | G47: =F47*$G$42/$F$42 -> #DIV/0! | H47: =F47*$H$7/$F$7 -> #DIV/0!
B48: Suporte de Prateleira Invisível 150mm | C48: UNIDADE | D48: 7 | E48: 0 | F48: =D48*E48 -> 0 | G48: =F48*$G$42/$F$42 -> #DIV/0! | H48: =F48*$H$7/$F$7 -> #DIV/0!
B49: Suporte de Cabide | C49: UNIDADE | D49: 3 | E49: 0 | F49: =D49*E49 -> 0 | G49: =F49*$G$42/$F$42 -> #DIV/0! | H49: =F49*$H$7/$F$7 -> #DIV/0!
B50: Cabideiro Barra de 3m | C50: METRO | D50: 20 | E50: 0 | F50: =D50*E50 -> 0 | G50: =F50*$G$42/$F$42 -> #DIV/0! | H50: =F50*$H$7/$F$7 -> #DIV/0!
B52: ELEMENTOS DE FIXAÇÃO E UNIÃO | F52: =SUM(F53:F59) -> 0 | G52: =F52*$G$42/$F$42 -> #DIV/0! | H52: =F52*$H$7/$F$7 -> #DIV/0!
B53: VB (Pino + VB 19mm) | C53: CONJUNTO | D53: 0 | E53: 0 | F53: =D53*E53 -> 0 | G53: =F53*$G$42/$F$42 -> #DIV/0! | H53: =F53*$H$7/$F$7 -> #DIV/0!
B54: Cavilha | C54: UNIDADE | D54: 0 | E54: 0 | F54: =D54*E54 -> 0 | G54: =F54*$G$42/$F$42 -> #DIV/0! | H54: =F54*$H$7/$F$7 -> #DIV/0!
B55: Parafuso | C55: UNIDADE | D55: 20 | F55: =D55*E55 -> 0 | G55: =F55*$G$42/$F$42 -> #DIV/0! | H55: =F55*$H$7/$F$7 -> #DIV/0!
B56: Kit Fixação (BUCHA + PARAFUSO + TAMPINHA = 4 CONJUNTOS) | C56: KIT | D56: 5.2 | F56: =D56*E56 -> 0 | G56: =F56*$G$42/$F$42 -> #DIV/0! | H56: =F56*$H$7/$F$7 -> #DIV/0!
B57: Cantoneira 3 Furos Níquelada + Capa Plástica (Unidade) | C57: CONJUNTO | D57: 0 | E57: 0 | F57: =D57*E57 -> 0 | G57: =F57*$G$42/$F$42 -> #DIV/0! | H57: =F57*$H$7/$F$7 -> #DIV/0!
B58: Cantoneira 3 Furos Dourada + Capa Plástica (Unidade) | C58: CONJUNTO | D58: 0 | E58: 0 | F58: =D58*E58 -> 0 | G58: =F58*$G$42/$F$42 -> #DIV/0! | H58: =F58*$H$7/$F$7 -> #DIV/0!
B60: ACABAMENTOS ( TAPA FURO E GOTAS DE SILICONE) | F60: =SUM(F61:F67) -> 0 | G60: =F60*$G$42/$F$42 -> #DIV/0! | H60: =F60*$H$7/$F$7 -> #DIV/0!
B61: Tapa Furo Branco 13mm (Cartela c. 50unidades) | C61: CARTELA - 50 UNID | D61: 8 | F61: =D61*E61 -> 0 | G61: =F61*$G$42/$F$42 -> #DIV/0! | H61: =F61*$H$7/$F$7 -> #DIV/0!
B62: Tapa Furo Branco 19mm (Cartela c. 25unidades) | C62: CARTELA - 25 UNID | D62: 0 | E62: 0 | F62: =D62*E62 -> 0 | G62: =F62*$G$42/$F$42 -> #DIV/0! | H62: =F62*$H$7/$F$7 -> #DIV/0!
B63: Tapa Furo Amadeirado 13mm (Cartela) | C63: CARTELA | D63: 0 | E63: 0 | F63: =D63*E63 -> 0 | G63: =F63*$G$42/$F$42 -> #DIV/0! | H63: =F63*$H$7/$F$7 -> #DIV/0!
B64: Passa Fio (Branco, Cinza ou Preto) | C64: UNIDADE | D64: 0 | E64: 0 | F64: =D64*E64 -> 0 | G64: =F64*$G$42/$F$42 -> #DIV/0! | H64: =F64*$H$7/$F$7 -> #DIV/0!
B65: Gota de Silicone Pequena (Unidade) | C65: UNIDADE | D65: 0 | E65: 0 | F65: =D65*E65 -> 0 | G65: =F65*$G$42/$F$42 -> #DIV/0! | H65: =F65*$H$7/$F$7 -> #DIV/0!
B66: Gota de Silicone Grande (Unidade) | C66: UNIDADE | D66: 0 | E66: 0 | F66: =D66*E66 -> 0 | G66: =F66*$G$42/$F$42 -> #DIV/0! | H66: =F66*$H$7/$F$7 -> #DIV/0!
B68: RODÍZIOS E PÉS | F68: =SUM(F69:F77) -> 0 | G68: =F68*$G$42/$F$42 -> #DIV/0! | H68: =F68*$H$7/$F$7 -> #DIV/0!
B69: Pé de Geladeira (Pequeno) | C69: UNIDADE | D69: 0 | E69: 0 | F69: =D69*E69 -> 0 | G69: =F69*$G$42/$F$42 -> #DIV/0! | H69: =F69*$H$7/$F$7 -> #DIV/0!
B70: Pé de Geladeira (Grande) | C70: UNIDADE | D70: 0 | E70: 0 | F70: =D70*E70 -> 0 | G70: =F70*$G$42/$F$42 -> #DIV/0! | H70: =F70*$H$7/$F$7 -> #DIV/0!
B72: Pés de Plásticos (Pequeno - 150mm) | C72: UNIDADE | D72: 0 | E72: 0 | F72: =D72*E72 -> 0 | G72: =F72*$G$42/$F$42 -> #DIV/0! | H72: =F72*$H$7/$F$7 -> #DIV/0!
B73: Pés de Plásticos (Grande - 200mm) | C73: UNIDADE | D73: 0 | E73: 0 | F73: =D73*E73 -> 0 | G73: =F73*$G$42/$F$42 -> #DIV/0! | H73: =F73*$H$7/$F$7 -> #DIV/0!
B75: Rodízio Diam. 50mm s/ Freio (Altura Final 65mm) | C75: UNIDADE | D75: 0 | E75: 0 | F75: =D75*E75 -> 0 | G75: =F75*$G$42/$F$42 -> #DIV/0! | H75: =F75*$H$7/$F$7 -> #DIV/0!
B76: Rodízio Diam. 50mm c/ Freio (Altura Final 65mm) | C76: UNIDADE | D76: 0 | E76: 0 | F76: =D76*E76 -> 0 | G76: =F76*$G$42/$F$42 -> #DIV/0! | H76: =F76*$H$7/$F$7 -> #DIV/0!
B78: ADESIVOS E SILICONES | F78: =SUM(F79:F89) -> 0 | G78: =F78*$G$42/$F$42 -> #DIV/0! | H78: =F78*$H$7/$F$7 -> #DIV/0!
B79: Selante Acrilico à base Água | C79: UNIDADE | D79: 0 | E79: 0 | F79: =D79*E79 -> 0 | G79: =F79*$G$42/$F$42 -> #DIV/0! | H79: =F79*$H$7/$F$7 -> #DIV/0!
B80: Silicone à base Água | C80: UNIDADE | D80: 0 | E80: 0 | F80: =D80*E80 -> 0 | G80: =F80*$G$42/$F$42 -> #DIV/0! | H80: =F80*$H$7/$F$7 -> #DIV/0!
B81: Silicone Incolor / Branco Acético | C81: UNIDADE | D81: 0 | E81: 0 | F81: =D81*E81 -> 0 | G81: =F81*$G$42/$F$42 -> #DIV/0! | H81: =F81*$H$7/$F$7 -> #DIV/0!
B82: Fixa Espelho | C82: UNIDADE | D82: 0 | E82: 0 | F82: =D82*E82 -> 0 | G82: =F82*$G$42/$F$42 -> #DIV/0! | H82: =F82*$H$7/$F$7 -> #DIV/0!
B83: PL 500 | C83: UNIDADE | D83: 0 | E83: 0 | F83: =D83*E83 -> 0 | G83: =F83*$G$42/$F$42 -> #DIV/0! | H83: =F83*$H$7/$F$7 -> #DIV/0!
B84: PL 600 | C84: UNIDADE | D84: 0 | E84: 0 | F84: =D84*E84 -> 0 | G84: =F84*$G$42/$F$42 -> #DIV/0! | H84: =F84*$H$7/$F$7 -> #DIV/0!
B85: Kleiberit | C85: UNIDADE | D85: 0 | E85: 0 | F85: =D85*E85 -> 0 | G85: =F85*$G$42/$F$42 -> #DIV/0! | H85: =F85*$H$7/$F$7 -> #DIV/0!
B86: Cola TRANSPARENTE FÓRMICA 2,5KG | C86: BALDINHO | D86: 140 | F86: =D86*E86 -> 0 | G86: =F86*$G$42/$F$42 -> #DIV/0! | H86: =F86*$H$7/$F$7 -> #DIV/0!
B87: Cola de Contato - 1/4 - Fórmica | C87: BALDINHO | D87: 25 | E87: 0 | F87: =D87*E87 -> 0 | G87: =F87*$G$42/$F$42 -> #DIV/0! | H87: =F87*$H$7/$F$7 -> #DIV/0!
B88: Cola Rápida (TEKBOND ou RENDIBOND) | C88: UNIDADE | D88: 15 | F88: =D88*E88 -> 0 | G88: =F88*$G$42/$F$42 -> #DIV/0! | H88: =F88*$H$7/$F$7 -> #DIV/0!
A91: PUXADORES | F91: =SUM(F92:F108) -> 0 | G91: 1 | H91: =F91*$H$7/$F$7 -> #DIV/0!
B92: Perfil Cava Rometal 15mm 6 METROS | C92: BARRA | D92: 70 | F92: =D92*E92 -> 0 | G92: =F92*$G$91/$F$91 -> #DIV/0! | H92: =F92*$H$7/$F$7 -> #DIV/0!
B93: Ponteira Cava Rometal | C93: PAR | D93: 8.5 | F93: =D93*E93 -> 0 | G93: =F93*$G$91/$F$91 -> #DIV/0! | H93: =F93*$H$7/$F$7 -> #DIV/0!
B95: PERFIL GOLA RCF 3 METROS | C95: BARRA | D95: 55 | E95: 0 | F95: =D95*E95 -> 0 | G95: =F95*$G$91/$F$91 -> #DIV/0! | H95: =F95*$H$7/$F$7 -> #DIV/0!
B96: PERFIL RM085 - PORTAS DE ABRIR - RM085 ROMETAL - INOX - 6 METROS | C96: BARRA | D96: 0 | E96: 0 | F96: =D96*E96 -> 0 | G96: =F96*$G$91/$F$91 -> #DIV/0! | H96: =F96*$H$7/$F$7 -> #DIV/0!
B98: PERFIL RM183 - PERFIL FACETATO - INOX - 6 METROS | C98: BARRA | D98: 0 | E98: 0 | F98: =D98*E98 -> 0 | G98: =F98*$G$91/$F$91 -> #DIV/0! | H98: =F98*$H$7/$F$7 -> #DIV/0!
B99: PERFIL RM183 - PONTEIRA CROMADA - INOX - 6 METROS | C99: PAR | D99: 0 | E99: 0 | F99: =D99*E99 -> 0 | G99: =F99*$G$91/$F$91 -> #DIV/0! | H99: =F99*$H$7/$F$7 -> #DIV/0!
B101: Puxador Quadradro haste 45 cm | C101: UNIADADE | D101: 17 | E101: 0 | F101: =D101*E101 -> 0 | G101: =F101*$G$91/$F$91 -> #DIV/0! | H101: =F101*$H$7/$F$7 -> #DIV/0!
B102: PERFIL GOLA RM | C102: BARRA | D102: 0 | E102: 0 | F102: =D102*E102 -> 0 | G102: =F102*$G$91/$F$91 -> #DIV/0! | H102: =F102*$H$7/$F$7 -> #DIV/0!
B103: PE | C103: BARRA | D103: 0 | E103: 0 | F103: =D103*E103 -> 0 | G103: =F103*$G$91/$F$91 -> #DIV/0! | H103: =F103*$H$7/$F$7 -> #DIV/0!
B104: PERFIL GOLA | C104: BARRA | D104: 0 | E104: 0 | F104: =D104*E104 -> 0 | G104: =F104*$G$91/$F$91 -> #DIV/0! | H104: =F104*$H$7/$F$7 -> #DIV/0!
B106: PONTEIRAS PARA PERFIL RM 175/190 - PONTEIRA INOX - 6 Metros (INOX) | C106: PAR | D106: 0 | E106: 0 | F106: =D106*E106 -> 0 | G106: =F106*$G$91/$F$91 -> #DIV/0! | H106: =F106*$H$7/$F$7 -> #DIV/0!
B107: PONTEIRAS PARA PERFIL RM 176/189 - PONTEIRA INOX - 6 Metros (INOX) | C107: PAR | D107: 0 | E107: 0 | F107: =D107*E107 -> 0 | G107: =F107*$G$91/$F$91 -> #DIV/0! | H107: =F107*$H$7/$F$7 -> #DIV/0!
A109: FERRAGENS | F109: =F110+F118+F126+F134+F140+F163 -> 0 | G109: 1 | H109: =F109*$H$7/$F$7 -> #DIV/0!
A110: TELESCÓPICA | F110: =SUM(F111:F117) -> 0 | G110: =F110*$G$109/$F$109 -> #DIV/0! | H110: =F110*$H$7/$F$7 -> #DIV/0!
B111: TELESCÓPICA 300MM | C111: UNIDADE | D111: 12 | E111: 0 | F111: =D111*E111 -> 0 | G111: =F111*$G$109/$F$109 -> #DIV/0! | H111: =F111*$H$7/$F$7 -> #DIV/0!
B112: TELESCÓPICA 350MM | C112: UNIDADE | D112: 13.5 | E112: 0 | F112: =D112*E112 -> 0 | G112: =F112*$G$109/$F$109 -> #DIV/0! | H112: =F112*$H$7/$F$7 -> #DIV/0!
B113: TELESCÓPICA 400MM | C113: UNIDADE | D113: 13.5 | F113: =D113*E113 -> 0 | G113: =F113*$G$109/$F$109 -> #DIV/0! | H113: =F113*$H$7/$F$7 -> #DIV/0!
B114: TELESCÓPICA 450MM | C114: UNIDADE | D114: 14 | E114: 0 | F114: =D114*E114 -> 0 | G114: =F114*$G$109/$F$109 -> #DIV/0! | H114: =F114*$H$7/$F$7 -> #DIV/0!
B115: TELESCÓPICA 500MM | C115: UNIDADE | D115: 15 | E115: 0 | F115: =D115*E115 -> 0 | G115: =F115*$G$109/$F$109 -> #DIV/0! | H115: =F115*$H$7/$F$7 -> #DIV/0!
B116: TELESCÓPICA 550MM | C116: UNIDADE | D116: 16 | E116: 0 | F116: =D116*E116 -> 0 | G116: =F116*$G$109/$F$109 -> #DIV/0! | H116: =F116*$H$7/$F$7 -> #DIV/0!
A118: TRILHO INVISÍVEL - PARCIAL | B118: TRILHO FECHO TOQUE | F118: =SUM(F119:F125) -> 0 | G118: =F118*$G$109/$F$109 -> #DIV/0! | H118: =F118*$H$7/$F$7 -> #DIV/0!
B119: TRILHO PARCIAL 300MM | C119: UNIDADE | D119: 0 | E119: 0 | F119: =D119*E119 -> 0 | G119: =F119*$G$109/$F$109 -> #DIV/0! | H119: =F119*$H$7/$F$7 -> #DIV/0!
B120: TRILHO PARCIAL 350MM | C120: UNIDADE | D120: 0 | E120: 0 | F120: =D120*E120 -> 0 | G120: =F120*$G$109/$F$109 -> #DIV/0! | H120: =F120*$H$7/$F$7 -> #DIV/0!
B121: TRILHO PARCIAL 400MM | C121: UNIDADE | D121: 27 | E121: 0 | F121: =D121*E121 -> 0 | G121: =F121*$G$109/$F$109 -> #DIV/0! | H121: =F121*$H$7/$F$7 -> #DIV/0!
...

Sheet PRODUÇÃO E MONTAGEM
B1: LEVANTAMENTO DE MATERIAIS | F1: DATA: | G1: ='CADASTRO CLIENTE'!C5 -> 10.01.20
F2: CLIENTE: | G2: ='CADASTRO CLIENTE'!C6 -> 0
B3: ATUALIZAÇÃO DA PLANILHA: | C3: ='CADASTRO CLIENTE'!E3 -> 10.01.20 | F3: EMPREENDIMENTO: | G3: ='CADASTRO CLIENTE'!C7 -> 0
B4: CUSTO FIXO - ESTIMADO | C4: 7200 | F4: AMBIENTE: | G4: ='CADASTRO CLIENTE'!C8 -> 0
B5: CONSIDERAR Nº DE DIAS UTÉIS NO MÊS: | C5: 22 | D5: =C4/C5 -> 327.27273 | F5: PRODUTO: | G5: ='CADASTRO CLIENTE'!C9 -> 0
B7: PRODUTO / MATERIAL | C7: UNIDADE | D7: CUSTOS | E7: QUANTIDADE | F7: CUSTO X QUANTIDADE | G7: % POR CATEGORIA | H7: % GLOBAL
A8: TOTAL | F8: =F9+F14+F19+F31+F38 -> 0 | H8: 1
A9: AJUSTE DE PROJETO | F9: =SUM(F10:F13) -> 0 | G9: 1 | H9: =F9*$H$8/$F$8 -> #DIV/0!
B10: MEDIDAS IN LOCCO | C10: HORA | D10: 15 | E10: 0 | F10: =D10*E10 -> 0 | G10: =F10*$G$9/$F$9 -> #DIV/0! | H10: =F10*$H$8/$F$8 -> #DIV/0!
B11: AJUSTE DE PROJETO (MODELAGEM) | C11: HORAS | D11: 15 | E11: 0 | F11: =D11*E11 -> 0 | G11: =F11*$G$9/$F$9 -> #DIV/0! | H11: =F11*$H$8/$F$8 -> #DIV/0!
B12: AJUSTE DE PROJETO (PRODUÇÃO) | C12: HORAS | D12: 15 | E12: 0 | F12: =D12*E12 -> 0 | G12: =F12*$G$9/$F$9 -> #DIV/0! | H12: =F12*$H$8/$F$8 -> #DIV/0!
A14: CARREGAMENTO E ORGANIZAÇÃO | F14: =SUM(F15:F18) -> 0 | G14: 1 | H14: =F14*$H$8/$F$8 -> #DIV/0!
B15: CARREGAMENTO EMPRESA - EQUIPE DE ENTREGA | C15: HORAS | D15: 30 | E15: 0 | F15: =D15*E15 -> 0 | G15: =F15*G14/F14 -> #DIV/0! | H15: =F15*$H$8/$F$8 -> #DIV/0!
B16: DESCARGA CASA DO CLIENTE - EQUIPE DE ENTREGA | C16: HORAS | D16: 0 | E16: 0 | F16: =D16*E16 -> 0 | G16: =F16*G15/F15 -> #DIV/0! | H16: =F16*$H$8/$F$8 -> #DIV/0!
B17: DESCARGA/ORGANIZAÇÃO FERRAMENTAS EMPRESA - EQUIPE DEMONTAGEM | C17: HORAS | D17: 0 | E17: 0 | F17: =D17*E17 -> 0 | G17: =F17*G16/F16 -> #DIV/0! | H17: =F17*$H$8/$F$8 -> #DIV/0!
A19: PRODUÇÃO EMPRESA | F19: =SUM(F20:F30) -> 0 | G19: 1 | H19: =F19*$H$8/$F$8 -> #DIV/0!
B20: PRODUÇÃO EMPRESA - CUSTO TOTAL DA PRODUÇÃO - DIA | C20: DIAS | D20: 409 | F20: =D20*E20 -> 0 | G20: =F20*$G$19/F19 -> #DIV/0! | H20: =F20*$H$8/$F$8 -> #DIV/0!
B21: PRODUÇÃO EMPRESA - CUSTO TOTAL DA PRODUÇÃO - HORAS | C21: HORA | D21: 0 | E21: 0 | F21: =D21*E21 -> 0 | G21: =F21*$G$19/F19 -> #DIV/0! | H21: =F21*$H$8/$F$8 -> #DIV/0!
B23: PRODUÇÃO EMPRESA - CUSTO DA EQUIPE A - TRABALHO EM CÉLULAS | C23: DIAS | D23: 0 | E23: 0 | F23: =D23*E23 -> 0 | G23: =F23*$G$19/F19 -> #DIV/0! | H23: =F23*$H$8/$F$8 -> #DIV/0!
B24: PRODUÇÃO EMPRESA - CUSTO DA EQUIPE B - TRABALHO EM CÉLULAS | C24: DIAS | D24: 0 | E24: 0 | F24: =D24*E24 -> 0 | G24: =F24*G19/F19 -> #DIV/0! | H24: =F24*$H$8/$F$8 -> #DIV/0!
B25: PRODUÇÃO EMPRESA - CUSTO DA EQUIPE C - TRABALHO EM CÉLULAS | C25: DIAS | D25: 0 | E25: 0 | F25: =D25*E25 -> 0 | G25: =F25*G19/F19 -> #DIV/0! | H25: =F25*$H$8/$F$8 -> #DIV/0!
B27: PRODUÇÃO COMISSIONADA - MARCENEIRO A | C27: VALOR | D27: 0 | E27: 0 | F27: =D27*E27 -> 0 | G27: =F27*$G$19/F19 -> #DIV/0! | H27: =F27*$H$8/$F$8 -> #DIV/0!
B28: PRODUÇÃO COMISSIONADA - MARCENEIRO B | C28: VALOR | D28: 0 | E28: 0 | F28: =D28*E28 -> 0 | G28: =F28*$G$19/F19 -> #DIV/0! | H28: =F28*$H$8/$F$8 -> #DIV/0!
B29: PRODUÇÃO COMISSIONADA - MARCENEIRO C | C29: VALOR | D29: 0 | E29: 0 | F29: =D29*E29 -> 0 | G29: =F29*$G$19/F19 -> #DIV/0! | H29: =F29*$H$8/$F$8 -> #DIV/0!
A31: MONTAGEM CASA DO CLIENTE | F31: =SUM(F32:F37) -> 0 | G31: 1 | H31: =F31*$H$8/$F$8 -> #DIV/0!
B32: MONTAGEM CASA DO CLIENTE - EQUIPE A (JOSÉ LUIZ E LUCAS) | C32: DIAS | D32: 409 | E32: 0 | F32: =D32*E32 -> 0 | G32: =F32*G31/F31 -> #DIV/0! | H32: =F32*$H$8/$F$8 -> #DIV/0!
B33: MONTAGEM CASA DO CLIENTE - EQUIPE B | C33: DIAS | D33: 0 | E33: 0 | F33: =D33*E33 -> 0 | G33: =F33*$G$31/F31 -> #DIV/0! | H33: =F33*$H$8/$F$8 -> #DIV/0!
B34: MONTAGEM CASA DO CLIENTE - EQUIPE C | C34: DIAS | D34: 0 | E34: 0 | F34: =D34*E34 -> 0 | G34: =F34*$G$31/F31 -> #DIV/0! | H34: =F34*$H$8/$F$8 -> #DIV/0!
B36: EQUIPE DE LIMPEZA E ENTREGA | C36: DIAS | D36: 0 | E36: 0 | F36: =D36*E36 -> 0 | G36: =F36*$G$31/F31 -> #DIV/0! | H36: =F36*$H$8/$F$8 -> #DIV/0!
A38: REGULAGENS + ASSISTÊNCIA TÉCNICA | F38: =SUM(F39:F41) -> 0 | G38: 1 | H38: =F38*$H$8/$F$8 -> #DIV/0!
B39: REGULAGENS DE PORTAS (MÉDIA 1 HORA DE SERVIÇO) + DESLOCAMENTO (1 HORA) | C39: Nº DE VEZES | D39: 50 | E39: 0 | F39: =D39*E39 -> 0 | G39: =F39*$G$38/F38 -> #DIV/0! | H39: =F39*$H$8/$F$8 -> #DIV/0!
B40: ASSISTÊNCIA TÉCNICA (MÉDIA 1,5 HORA DE SERVIÇO) + DESLOCAMENTO (1 HORA) | C40: Nº DE VEZES | D40: 0 | E40: 0 | F40: =D40*E40 -> 0 | G40: =F40*$G$39/F39 -> #DIV/0! | H40: =F40*$H$8/$F$8 -> #DIV/0!

Sheet PREÇO DE VENDA
B1: PLANILHA DE FORMAÇÃO DE PREÇO DE VENDA | F1: PREÇO DE VENDA P/ ORÇAMENTO
C2: ATUALIZAÇÃO DA PLANILHA: | D2: ='CADASTRO CLIENTE'!E3 -> 10.01.20 | F2: FORMA DE PAGAMEN. | G2: VALOR | H2: PARCELA
B3: DATA: | C3: ='CADASTRO CLIENTE'!C5 -> 10.01.20 | F3: À VISTA | G3: =D54 -> 0 | H3: 50% + 50%
B4: CLIENTE: | C4: ='CADASTRO CLIENTE'!C6 -> 0 | F4: À PRAZO 10% | G4: =(G3)/0.885 -> 0
B5: EMPREENDIMENTO: | C5: ='CADASTRO CLIENTE'!C7 -> 0 | F5: 3X | G5: =D58 -> 0 | H5: =G58 -> 0
B6: AMBIENTE: | C6: ='CADASTRO CLIENTE'!C8 -> 0 | F6: 6X | G6: =D61 -> 0 | H6: =G61 -> 0
B7: PRODUTO: | C7: ='CADASTRO CLIENTE'!C9 -> 0 | F7: 8X | G7: =D63 -> 0 | H7: =G63 -> 0
A8: PARÂMETROS DA EMPRESA | F8: 10X | G8: =D65 -> 0 | H8: =G65 -> 0
A10: IMPOSTOS | B10: SUPER SIMPLES | C10: 0.04 | D10: =$C$31*C10 -> 0
A11: OUTROS | B11: COMISSÕES | C11: 0.03 | D11: =$C$31*C11 -> 0
B12: FRETE | C12: 0 | D12: =$C$31*C12 -> 0
B13: OUTROS | C13: 0.015 | D13: =$C$31*C13 -> 0
A14: CUSTOS VARIÁVEIS TOTAIS | C14: =SUM(C10:C13) -> 0.085 | D14: =SUM(D10:D13) -> 0
A15: LUCRATIVIDADE | C15: 0.15 | D15: =C15*$C$31 -> 0
A17: PARÂMETROS DE CUSTO DO PRODUTO
A18: CUSTO DO MATERIAL | C18: =D18*$C$26/$D$26 -> #DIV/0! | D18: =MATERIAIS!F7 -> 0
B19: AJUSTE DE PROJETO | C19: =D19*$C$26/$D$26 -> #DIV/0! | D19: ='PRODUÇÃO E MONTAGEM'!F9 -> 0
A20: CUSTO CARREGAMENTO E ORGANIZAÇÃO | C20: =D20*$C$26/$D$26 -> #DIV/0! | D20: ='PRODUÇÃO E MONTAGEM'!F14 -> 0
A21: CUSTO DE PRODUÇÃO | C21: =D21*$C$26/$D$26 -> #DIV/0! | D21: ='PRODUÇÃO E MONTAGEM'!F19 -> 0
B22: CUSTO DE MONTAGEM | C22: =D22*$C$26/$D$26 -> #DIV/0! | D22: ='PRODUÇÃO E MONTAGEM'!F31 -> 0
B23: CUSTO ASSISTÊNCIA TÉCNICA | C23: =D23*$C$26/$D$26 -> #DIV/0! | D23: ='PRODUÇÃO E MONTAGEM'!F38 -> 0
A24: CUSTO DO PRODUTO | C24: =D24*$C$26/$D$26 -> #DIV/0! | D24: =SUM(D18:D23) -> 0
B25: OUTROS: | C25: =D25*$C$26/$D$26 -> #DIV/0! | D25: 0
A26: CÁLCULO DOS CUSTOS : TOTAL | C26: 1 | D26: =D24+D25 -> 0
A28: CÁLCULO PREÇO DE VENDA
A29: MARK - UP | C29: =1/(1-(C14+C15)) -> 1.3071895
A31: PREÇO DE VENDA | C31: =($D$26)*C29 -> 0 | D31: 1
A32: IMPOSTO | C32: =D10 -> 0 | D32: =C32*$D$31/$C$31 -> #DIV/0!
A33: CUSTO DO MATERIAL | C33: =D18 -> 0 | D33: =C33*$D$31/$C$31 -> #DIV/0!
A34: CUSTO DO PRODUÇÃO E MONTAGEM | C34: =D21+D22+D20+D23 -> 0 | D34: =C34*$D$31/$C$31 -> #DIV/0!
A35: CUSTO MAT. + PROCESSO + IMPOSTO | C35: =C33+C34+D10 -> 0 | D35: =C35*$D$31/$C$31 -> #DIV/0!
A36: LUCRATIVIDADE | C36: =D15 -> 0 | D36: =C36*$D$31/$C$31 -> #DIV/0!
A38: PREÇO DE VENDA X RELAÇÃO COM MATERIAL
A39: PREÇO DE VENDA/MATERIAL : | C39: =C31/C33 -> #DIV/0! | D39: =C31 -> 0
A40: ESTUDO MULTIPLICADOR X MATERIAL: | C40: 3 | D40: =C33*C40 -> 0
A41: DIFERENÇA PREÇO DE VENDA E INDICADO: | D41: =D40-C31 -> 0
B45: PLANILHA DE FORMAÇÃO DE PREÇO DE VENDA
C46: ATUALIZAÇÃO DA PLANILHA: | D46: =D2 -> 10.01.20
B48: CLIENTE: | C48: =C4 -> 0
B49: PRODUTO: | C49: =C5 -> 0
B50: AMBIENTE: | C50: =C6 -> 0
A52: TABELA VENDA À VISTA | C52: % | D52: VALOR | F52: Valor da Entrada | G52: Valor da Entrega
A53: PREÇO DE VENDA - FINAL | C53: 0 | D53: =C31 -> 0 | F53: =D53*0.7 -> 0 | G53: =D53*0.3 -> 0
A54: PREÇO DE VENDA - COM 3,33% DESCONTO | C54: 0 | D54: =(D53/(100-C54))*100 -> 0 | F54: =D54*0.7 -> 0 | G54: =F54*0.3 -> 0
A57: TABELA VENDA A PRAZO | C57: MULTIPLI. | D57: VALOR TOTAL | F57: VALOR PARCELA | G57: Nº DE PARCELAS | H57: Final
A58: PREÇO DE VENDA 3X | C58: 0.3432 | D58: =G58*F58 -> 0 | F58: 3 | G58: =$D$54*C58 -> 0 | H58: 0.054
A59: PREÇO DE VENDA 4X | C59: 0.2612 | D59: =G59*F59 -> 0 | F59: 4 | G59: =$D$54*C59 -> 0 | H59: 0.063
A60: PREÇO DE VENDA 5X | C60: 0.212 | D60: =G60*F60 -> 0 | F60: 5 | G60: =$D$54*C60 -> 0 | H60: 0.071
A61: PREÇO DE VENDA 6X | C61: 0.1792 | D61: =G61*F61 -> 0 | F61: 6 | G61: =$D$54*C61 -> 0 | H61: 0.08
A62: PREÇO DE VENDA 7X | C62: 0.1558 | D62: =G62*F62 -> 0 | F62: 7 | G62: =$D$54*C62 -> 0 | H62: 0.089
A63: PREÇO DE VENDA 8X | C63: 0.1383 | D63: =G63*F63 -> 0 | F63: 8 | G63: =$D$54*C63 -> 0 | H63: 0.097
A64: PREÇO DE VENDA 9X | C64: 0.1247 | D64: =G64*F64 -> 0 | F64: 9 | G64: =$D$54*C64 -> 0 | H64: 0.106
A65: PREÇO DE VENDA 10X | C65: 0.1138 | D65: =G65*F65 -> 0 | F65: 10 | G65: =$D$54*C65 -> 0 | H65: 0.114
A66: PREÇO DE VENDA 11X | C66: 0.1049 | D66: =G66*F66 -> 0 | F66: 11 | G66: =$D$54*C66 -> 0 | H66: 0.123
A67: PREÇO DE VENDA 12X | C67: 0.0975 | D67: =G67*F67 -> 0 | F67: 12 | G67: =$D$54*C67 -> 0 | H67: 0.129
